cli.py
simple_file_checksum.py
simple_file_checksum-1.3.0.dist-info/LICENCE
simple_file_checksum-1.3.0.dist-info/METADATA
simple_file_checksum-1.3.0.dist-info/WHEEL
simple_file_checksum-1.3.0.dist-info/entry_points.txt
simple_file_checksum-1.3.0.dist-info/top_level.txt
simple_file_checksum-1.3.0.dist-info/RECORD
