Metadata-Version: 2.1
Name: simple-file-checksum
Version: 1.3.0
Summary: Returns the MD5, SHA1, SHA256, SHA384, or SHA512 checksum of a file.
Home-page: https://github.com/shash873/simple-file-checksum
Author: Shash Sinha
Author-email: shash873@gmail.com
License: MIT
Classifier: Programming Language :: Python :: 3.9
Classifier: Programming Language :: Python :: 3.10
Classifier: Programming Language :: Python :: 3.11
Classifier: Programming Language :: Python :: 3.12
Classifier: Programming Language :: Python :: 3.13
Classifier: Development Status :: 5 - Production/Stable
Classifier: Operating System :: MacOS
Classifier: Operating System :: POSIX :: Linux
Classifier: Operating System :: Microsoft :: Windows
Classifier: Topic :: Security :: Cryptography
Classifier: Topic :: Utilities
Classifier: License :: OSI Approved :: MIT License
Requires-Python: >=3.9
License-File: LICENCE
Provides-Extra: dev
Requires-Dist: pytest>=3.9; extra == "dev"
Requires-Dist: pytest-cov; extra == "dev"
Requires-Dist: tox==4.22.0; extra == "dev"
